{"nodes": [{"id": "c_users_stem_desktop_verificacion_pagos_app_lib_store_ts", "label": "store.ts", "file_type": "code", "source_file": "C:\\Users\\STEM\\Desktop\\verificacion-pagos-app\\lib\\store.ts", "source_location": "L1"}, {"id": "lib_store_wizardstate", "label": "WizardState", "file_type": "code", "source_file": "C:\\Users\\STEM\\Desktop\\verificacion-pagos-app\\lib\\store.ts", "source_location": "L13"}, {"id": "lib_store_initial_state", "label": "INITIAL_STATE", "file_type": "code", "source_file": "C:\\Users\\STEM\\Desktop\\verificacion-pagos-app\\lib\\store.ts", "source_location": "L31"}, {"id": "lib_store_usewizardstore", "label": "useWizardStore", "file_type": "code", "source_file": "C:\\Users\\STEM\\Desktop\\verificacion-pagos-app\\lib\\store.ts", "source_location": "L55"}], "edges": [{"source": "c_users_stem_desktop_verificacion_pagos_app_lib_store_ts", "target": "zustand", "relation": "imports_from", "context": "import", "confidence": "EXTRACTED", "source_file": "C:\\Users\\STEM\\Desktop\\verificacion-pagos-app\\lib\\store.ts", "source_location": "L1", "weight": 1.0}, {"source": "c_users_stem_desktop_verificacion_pagos_app_lib_store_ts", "target": "middleware", "relation": "imports_from", "context": "import", "confidence": "EXTRACTED", "source_file": "C:\\Users\\STEM\\Desktop\\verificacion-pagos-app\\lib\\store.ts", "source_location": "L2", "weight": 1.0}, {"source": "c_users_stem_desktop_verificacion_pagos_app_lib_store_ts", "target": "c_users_stem_desktop_verificacion_pagos_app_lib_types_ts", "relation": "imports_from", "context": "import", "confidence": "EXTRACTED", "source_file": "C:\\Users\\STEM\\Desktop\\verificacion-pagos-app\\lib\\store.ts", "source_location": "L3", "weight": 1.0}, {"source": "c_users_stem_desktop_verificacion_pagos_app_lib_store_ts", "target": "lib_types_extracteddata", "relation": "imports", "context": "import", "confidence": "EXTRACTED", "source_file": "C:\\Users\\STEM\\Desktop\\verificacion-pagos-app\\lib\\store.ts", "source_location": "L3", "weight": 1.0}, {"source": "c_users_stem_desktop_verificacion_pagos_app_lib_store_ts", "target": "lib_types_manualformdata", "relation": "imports", "context": "import", "confidence": "EXTRACTED", "source_file": "C:\\Users\\STEM\\Desktop\\verificacion-pagos-app\\lib\\store.ts", "source_location": "L3", "weight": 1.0}, {"source": "c_users_stem_desktop_verificacion_pagos_app_lib_store_ts", "target": "lib_types_rawpdftext", "relation": "imports", "context": "import", "confidence": "EXTRACTED", "source_file": "C:\\Users\\STEM\\Desktop\\verificacion-pagos-app\\lib\\store.ts", "source_location": "L3", "weight": 1.0}, {"source": "c_users_stem_desktop_verificacion_pagos_app_lib_store_ts", "target": "lib_types_uploadeddocuments", "relation": "imports", "context": "import", "confidence": "EXTRACTED", "source_file": "C:\\Users\\STEM\\Desktop\\verificacion-pagos-app\\lib\\store.ts", "source_location": "L3", "weight": 1.0}, {"source": "c_users_stem_desktop_verificacion_pagos_app_lib_store_ts", "target": "lib_types_wizardstep", "relation": "imports", "context": "import", "confidence": "EXTRACTED", "source_file": "C:\\Users\\STEM\\Desktop\\verificacion-pagos-app\\lib\\store.ts", "source_location": "L3", "weight": 1.0}, {"source": "c_users_stem_desktop_verificacion_pagos_app_lib_store_ts", "target": "lib_store_wizardstate", "relation": "contains", "confidence": "EXTRACTED", "source_file": "C:\\Users\\STEM\\Desktop\\verificacion-pagos-app\\lib\\store.ts", "source_location": "L13", "weight": 1.0}, {"source": "c_users_stem_desktop_verificacion_pagos_app_lib_store_ts", "target": "lib_store_initial_state", "relation": "contains", "confidence": "EXTRACTED", "source_file": "C:\\Users\\STEM\\Desktop\\verificacion-pagos-app\\lib\\store.ts", "source_location": "L31", "weight": 1.0}, {"source": "c_users_stem_desktop_verificacion_pagos_app_lib_store_ts", "target": "lib_store_usewizardstore", "relation": "contains", "confidence": "EXTRACTED", "source_file": "C:\\Users\\STEM\\Desktop\\verificacion-pagos-app\\lib\\store.ts", "source_location": "L55", "weight": 1.0}], "raw_calls": []}